nanopb_helpers/__init__.py
nanopb_helpers/__init__.py~
nanopb_helpers/bin/__init__.py
nanopb_helpers/bin/nanopb-0.3.2-linux-x86/.gitignore
nanopb_helpers/bin/nanopb-0.3.2-linux-x86/CHANGELOG.txt
nanopb_helpers/bin/nanopb-0.3.2-linux-x86/LICENSE.txt
nanopb_helpers/bin/nanopb-0.3.2-linux-x86/pb.h
nanopb_helpers/bin/nanopb-0.3.2-linux-x86/pb_common.c
nanopb_helpers/bin/nanopb-0.3.2-linux-x86/pb_common.h
nanopb_helpers/bin/nanopb-0.3.2-linux-x86/pb_decode.c
nanopb_helpers/bin/nanopb-0.3.2-linux-x86/pb_decode.h
nanopb_helpers/bin/nanopb-0.3.2-linux-x86/pb_encode.c
nanopb_helpers/bin/nanopb-0.3.2-linux-x86/pb_encode.h
nanopb_helpers/bin/nanopb-0.3.2-linux-x86/README.txt
nanopb_helpers/bin/nanopb-0.3.2-linux-x86/docs/concepts.rst
nanopb_helpers/bin/nanopb-0.3.2-linux-x86/docs/generator_flow.svg
nanopb_helpers/bin/nanopb-0.3.2-linux-x86/docs/index.rst
nanopb_helpers/bin/nanopb-0.3.2-linux-x86/docs/lsr.css
nanopb_helpers/bin/nanopb-0.3.2-linux-x86/docs/Makefile
nanopb_helpers/bin/nanopb-0.3.2-linux-x86/docs/menu.rst
nanopb_helpers/bin/nanopb-0.3.2-linux-x86/docs/migration.rst
nanopb_helpers/bin/nanopb-0.3.2-linux-x86/docs/reference.rst
nanopb_helpers/bin/nanopb-0.3.2-linux-x86/docs/security.rst
nanopb_helpers/bin/nanopb-0.3.2-linux-x86/docs/logo/logo.png
nanopb_helpers/bin/nanopb-0.3.2-linux-x86/docs/logo/logo.svg
nanopb_helpers/bin/nanopb-0.3.2-linux-x86/docs/logo/logo16px.png
nanopb_helpers/bin/nanopb-0.3.2-linux-x86/docs/logo/logo48px.png
nanopb_helpers/bin/nanopb-0.3.2-linux-x86/examples/network_server/client.c
nanopb_helpers/bin/nanopb-0.3.2-linux-x86/examples/network_server/common.c
nanopb_helpers/bin/nanopb-0.3.2-linux-x86/examples/network_server/common.h
nanopb_helpers/bin/nanopb-0.3.2-linux-x86/examples/network_server/fileproto.options
nanopb_helpers/bin/nanopb-0.3.2-linux-x86/examples/network_server/fileproto.proto
nanopb_helpers/bin/nanopb-0.3.2-linux-x86/examples/network_server/Makefile
nanopb_helpers/bin/nanopb-0.3.2-linux-x86/generator-bin/protobuf-2.6.1-py2.7.egg/EGG-INFO/dependency_links.txt
nanopb_helpers/bin/nanopb-0.3.2-linux-x86/generator-bin/protobuf-2.6.1-py2.7.egg/EGG-INFO/namespace_packages.txt
nanopb_helpers/bin/nanopb-0.3.2-linux-x86/generator-bin/protobuf-2.6.1-py2.7.egg/EGG-INFO/PKG-INFO
nanopb_helpers/bin/nanopb-0.3.2-linux-x86/generator-bin/protobuf-2.6.1-py2.7.egg/EGG-INFO/requires.txt
nanopb_helpers/bin/nanopb-0.3.2-linux-x86/generator-bin/protobuf-2.6.1-py2.7.egg/EGG-INFO/SOURCES.txt
nanopb_helpers/bin/nanopb-0.3.2-linux-x86/generator-bin/protobuf-2.6.1-py2.7.egg/EGG-INFO/top_level.txt
nanopb_helpers/bin/nanopb-0.3.2-linux-x86/generator-bin/protobuf-2.6.1-py2.7.egg/EGG-INFO/zip-safe
nanopb_helpers-0.3.post2.dist-info/DESCRIPTION.rst
nanopb_helpers-0.3.post2.dist-info/METADATA
nanopb_helpers-0.3.post2.dist-info/metadata.json
nanopb_helpers-0.3.post2.dist-info/RECORD
nanopb_helpers-0.3.post2.dist-info/top_level.txt
nanopb_helpers-0.3.post2.dist-info/WHEEL
