Metadata-Version: 2.0
Name: nanopb-helpers
Version: 0.3.post2
Summary: Cross-platform Python API for `nanopb`
Home-page: http://github.com/wheeler-microfluidics/nanopb_helpers.git
Author: Christian Fobel
Author-email: christian@fobel.net
License: GPLv2
Platform: UNKNOWN
Requires-Dist: path-helpers
